qt6_applications/__init__.py
qt6_applications/_applications.py
qt6_applications/_version.py
qt6_applications/Qt/bin/androiddeployqt
qt6_applications/Qt/bin/androiddeployqt6
qt6_applications/Qt/bin/androidtestrunner
qt6_applications/Qt/bin/assistant
qt6_applications/Qt/bin/designer
qt6_applications/Qt/bin/lconvert
qt6_applications/Qt/bin/linguist
qt6_applications/Qt/bin/lrelease
qt6_applications/Qt/bin/lupdate
qt6_applications/Qt/bin/pixeltool
qt6_applications/Qt/bin/qdbus
qt6_applications/Qt/bin/qdbuscpp2xml
qt6_applications/Qt/bin/qdbusviewer
qt6_applications/Qt/bin/qdbusxml2cpp
qt6_applications/Qt/bin/qdistancefieldgenerator
qt6_applications/Qt/bin/qdoc
qt6_applications/Qt/bin/qmake
qt6_applications/Qt/bin/qmake6
qt6_applications/Qt/bin/qml
qt6_applications/Qt/bin/qmldom
qt6_applications/Qt/bin/qmleasing
qt6_applications/Qt/bin/qmlformat
qt6_applications/Qt/bin/qmllint
qt6_applications/Qt/bin/qmlls
qt6_applications/Qt/bin/qmlplugindump
qt6_applications/Qt/bin/qmlpreview
qt6_applications/Qt/bin/qmlprofiler
qt6_applications/Qt/bin/qmlscene
qt6_applications/Qt/bin/qmltc
qt6_applications/Qt/bin/qmltestrunner
qt6_applications/Qt/bin/qmltime
qt6_applications/Qt/bin/qt-cmake
qt6_applications/Qt/bin/qt-configure-module
qt6_applications/Qt/bin/qtdiag
qt6_applications/Qt/bin/qtdiag6
qt6_applications/Qt/bin/qtpaths
qt6_applications/Qt/bin/qtpaths6
qt6_applications/Qt/bin/qtplugininfo
qt6_applications/Qt/lib/libQt6Core.so.6
qt6_applications/Qt/lib/libQt6DBus.so.6
qt6_applications/Qt/lib/libQt6Designer.so.6
qt6_applications/Qt/lib/libQt6DesignerComponents.so.6
qt6_applications/Qt/lib/libQt6EglFSDeviceIntegration.so.6
qt6_applications/Qt/lib/libQt6Gui.so.6
qt6_applications/Qt/lib/libQt6Help.so.6
qt6_applications/Qt/lib/libQt6Network.so.6
qt6_applications/Qt/lib/libQt6OpenGL.so.6
qt6_applications/Qt/lib/libQt6OpenGLWidgets.so.6
qt6_applications/Qt/lib/libQt6PrintSupport.so.6
qt6_applications/Qt/lib/libQt6Qml.so.6
qt6_applications/Qt/lib/libQt6QmlCompiler.so.6
qt6_applications-6.5.0.2.3.dist-info/COPYING
qt6_applications-6.5.0.2.3.dist-info/METADATA
qt6_applications-6.5.0.2.3.dist-info/WHEEL
qt6_applications-6.5.0.2.3.dist-info/top_level.txt
qt6_applications-6.5.0.2.3.dist-info/RECORD
